haplotyping/__init__.py
haplotyping/_version.py
haplotyping/general.py
haplotyping/api/__init__.py
haplotyping/api/api.py
haplotyping/data/__init__.py
haplotyping/data/checkDatabase.py
haplotyping/data/constructDatabase.py
haplotyping/data/validator.py
haplotyping/data/schema/data_default_experiments.schema.json
haplotyping/data/schema/data_default_mappings.schema.json
haplotyping/data/schema/data_default_markers.schema.json
haplotyping/data/schema/data_default_metadata.schema.json
haplotyping/data/schema/data_default_scores.schema.json
haplotyping/data/schema/data_default_sequences.schema.json
haplotyping/data/schema/data_default_varieties.schema.json
haplotyping/data/schema/index_ancestors.schema.json
haplotyping/data/schema/index_breeders.schema.json
haplotyping/data/schema/index_countries.schema.json
haplotyping/data/schema/index_species.schema.json
haplotyping/data/schema/index_synonyms.schema.json
haplotyping/data/schema/index_varieties.schema.json
haplotyping/graph/__init__.py
haplotyping/graph/api.py
haplotyping/graph/baseGraph.py
haplotyping/graph/sections.py
haplotyping/graph/sequence.py
haplotyping/index/__init__.py
haplotyping/index/connections.py
haplotyping/index/database.py
haplotyping/index/splits.py
haplotyping/index/storage.py
haplotyping/service/__init__.py
haplotyping/service/api.py
haplotyping/service/api_collection.py
haplotyping/service/api_country.py
haplotyping/service/api_dataset.py
haplotyping/service/api_kmer.py
haplotyping/service/api_marker.py
haplotyping/service/api_split.py
haplotyping/service/api_tools.py
haplotyping/service/api_variety.py
haplotyping/service/kmer_kmc.py
haplotyping/service/marker.py
haplotyping/service/split.py
haplotyping-0.0.17.dist-info/LICENSE
haplotyping-0.0.17.dist-info/METADATA
haplotyping-0.0.17.dist-info/WHEEL
haplotyping-0.0.17.dist-info/top_level.txt
haplotyping-0.0.17.dist-info/RECORD
