Metadata-Version: 2.1
Name: haplotyping
Version: 0.0.17
Summary: Haplotyping
Home-page: https://github.com/haplotyping/haplotyping
Author: Matthijs Brouwer
Author-email: matthijs.brouwer@wur.nl
Classifier: Programming Language :: Python :: 3
Classifier: Operating System :: OS Independent
Requires-Python: >=3.11
License-File: LICENSE
Requires-Dist: graphviz >=0.20.1
Requires-Dist: pandas >=2.1.0
Requires-Dist: numpy >=1.25.2
Requires-Dist: networkit >=10.1
Requires-Dist: h5py >=3.9.0
Requires-Dist: tables >=3.8.0
Requires-Dist: pyahocorasick >=2.0.0
Requires-Dist: Flask ==2.3.3
Requires-Dist: flask-restx ==1.2.0
Requires-Dist: waitress >=2.1.2
Requires-Dist: Flask-caching >=2.0.2
Requires-Dist: openpyxl >=3.1.2
Requires-Dist: frictionless ==5.10.5
Requires-Dist: psutil >=5.9.5
Requires-Dist: metis >=0.2a5
